lb/__init__.py
lb-0.0.4.dist-info/LICENSE
lb-0.0.4.dist-info/METADATA
lb-0.0.4.dist-info/WHEEL
lb-0.0.4.dist-info/top_level.txt
lb-0.0.4.dist-info/RECORD
