Metadata-Version: 2.1
Name: lb
Version: 0.0.4
Summary: utils for ipython importing
Home-page: https://github.com/thorwhalen/uu/tree/master/lb
Author: Thor Whalen
License: apache-2.0
Platform: any
License-File: LICENSE
